[
  {
    "userId": "630599",
    "userAddress": "0xed64d6e26d0385279179270dd9b517642b9ed2a2",
    "profileDisplayName": "Amelia Brown",
    "profileHandle": "jenniferallen",
    "connectedAddresses": [
      {
        "address": "2Nqa82mQ6yBnc2hjJ44Efh6UDgfUUtWt9imTfF6AjKSQ",
        "chainId": "900"
      },
      {
        "address": "0x40c54929e8a03cb4787241cc4289b73413230c69",
        "chainId": "1"
      }
    ]
  },
  {
    "userId": "630600",
    "userAddress": "0x1521ad294cb9d78e3fa9955aefd9e5dda116c988",
    "profileDisplayName": "Bartholomeüs ",
    "profileHandle": "ciergi",
    "connectedAddresses": [
      {
        "address": "0x718dd98cff85f88f6f6682572f8cee3340ceb4c0",
        "chainId": "1"
      }
    ]
  },
  {
    "userId": "630601",
    "userAddress": "0xf9d6ce18052b5ca58b032ea72aca1d0478d1ae22",
    "profileDisplayName": "Peace 🕊️ & 🦅 Freedom",
    "profileHandle": "peacefreedom.eth",
    "connectedAddresses": [
      {
        "address": "0xa9ea89270c5c64cc9bfcede9b8bb1c5b76b4b448",
        "chainId": "1"
      }
    ]
  },
  {
    "userId": "630602",
    "userAddress": "0x1beaab774f1b06ddfbc074c5af4f00b0723aeccc",
    "profileDisplayName": "SelenaJ09003477",
    "profileHandle": "selenaj09003477",
    "connectedAddresses": [
      {
        "address": "0x0631c259e0d330628902062a26f39740beef15b5",
        "chainId": "1"
      }
    ]
  },
  {
    "userId": "630603",
    "userAddress": "0x138231f0d915bbf064ac6e51d8f84175b4940843",
    "profileDisplayName": "Agbaje Abiola",
    "profileHandle": "spacejr09",
    "connectedAddresses": [
      {
        "address": "0x7e1ea3a27a01aadd3c6886c6cc1323c630d46b8e",
        "chainId": "1"
      }
    ]
  },
  {
    "userId": "630604",
    "userAddress": "0x1ef82165b2b79c8e63b3bf4c2bb87a9dfdd6b6eb",
    "profileDisplayName": "Homoousia",
    "profileHandle": "homoousia",
    "connectedAddresses": [
      {
        "address": "0x1a0629e66e871c11847d8e55eeb09fc70de0871e",
        "chainId": "1"
      }
    ]
  },
  {
    "userId": "630605",
    "userAddress": "0x3bfdcb7bd83c66b09b51140b96f1406b1269f52e",
    "profileDisplayName": "Grace",
    "profileHandle": "gzhong",
    "connectedAddresses": []
  },
  {
    "userId": "630606",
    "userAddress": "0x46ab57f7bb90bfbe7b2b9bfe3e98561b7177d528",
    "profileDisplayName": "",
    "profileHandle": "used649",
    "connectedAddresses": [
      {
        "address": "0x46ab57f7bb90bfbe7b2b9bfe3e98561b7177d528",
        "chainId": "1"
      }
    ]
  },
  {
    "userId": "630607",
    "userAddress": "0x9c0b6a5ef5f3d44a903ae8665a86c73d2c5c6de9",
    "profileDisplayName": "Ville",
    "profileHandle": "winningville",
    "connectedAddresses": []
  },
  {
    "userId": "630608",
    "userAddress": "0x5053eebae7674d07704fc9f60c99fd97079cfbc2",
    "profileDisplayName": "DreamCatcher",
    "profileHandle": "vhfjvb",
    "connectedAddresses": [
      {
        "address": "0x98d1c3ade25d773952725f4105dc13641e807ac0",
        "chainId": "1"
      }
    ]
  },
  {
    "userId": "630609",
    "userAddress": "0xcfa2c25072e134cc3676e9bc3e224cad0381f5de",
    "profileDisplayName": "888fm",
    "profileHandle": "888fm",
    "connectedAddresses": [
      {
        "address": "0xe5329ed8b7bd20ba44f0e52c10cbd3f7d0b2ecb7",
        "chainId": "1"
      }
    ]
  },
  {
    "userId": "630610",
    "userAddress": "0xfdcd30870da562e4bcd120c6df9edfb4b150432d",
    "profileDisplayName": "Orhideya",
    "profileHandle": "orhideya",
    "connectedAddresses": []
  },
  {
    "userId": "630611",
    "userAddress": "0x7103835d52bec892389e9f726077ed2bb7a5695e",
    "profileDisplayName": "b1720",
    "profileHandle": "b1720",
    "connectedAddresses": [
      {
        "address": "0x79a5189e8a02895a3db7f5d07031545c4e6b1720",
        "chainId": "1"
      },
      {
        "address": "6yMYNRGhckEopM28v1UvKujhncYrKvj1abu8MEkiRL55",
        "chainId": "900"
      }
    ]
  },
  {
    "userId": "630614",
    "userAddress": "0x49685dc470d06db11a6b06190ec871c1de00c11f",
    "profileDisplayName": "enowelin",
    "profileHandle": "enowelinschush",
    "connectedAddresses": [
      {
        "address": "0x4583ef23d7f3f3af4cc706c1cb0d069c47221b92",
        "chainId": "1"
      }
    ]
  },
  {
    "userId": "630615",
    "userAddress": "0x44c9cab0f61819ac4700440bb82a0b315125a460",
    "profileDisplayName": "The ₿itcoin Therapist",
    "profileHandle": "thebtctherapist",
    "connectedAddresses": [
      {
        "address": "0x5c2fc8132159742f57a82f2f3ff2e2268b4d52ed",
        "chainId": "1"
      },
      {
        "address": "AtJDFqUbTrFeB8f6qi1DzWfw8nCcWqNosC4wXS5THvud",
        "chainId": "900"
      }
    ]
  },
  {
    "userId": "630616",
    "userAddress": "0x70de66eefb36dc403cd6f8f3060efa1d8ec8a91a",
    "profileDisplayName": "chromiss",
    "profileHandle": "chromiss",
    "connectedAddresses": [
      {
        "address": "0x466afd5e9a0da88d22165d399050ac2527e7b068",
        "chainId": "1"
      },
      {
        "address": "7K4ZxoTDwtQjnyNgAUSpgJYrDd92uHDorBWrhgt6E1id",
        "chainId": "900"
      }
    ]
  },
  {
    "userId": "630617",
    "userAddress": "0x90612b5c7e5f79bdb76be4ed3da7063370e1479e",
    "profileDisplayName": "Moscox ",
    "profileHandle": "moscoxchange",
    "connectedAddresses": [
      {
        "address": "0xd9f86ede883106e0f14a85e0ed9d4f34b3ac4eb3",
        "chainId": "1"
      }
    ]
  },
  {
    "userId": "630618",
    "userAddress": "0x4421a8266b90334d05cb5202fba480491c161108",
    "profileDisplayName": "nininihao",
    "profileHandle": "nihao16",
    "connectedAddresses": [
      {
        "address": "0x98833036a2ddeb1652e519d5c780d36c3212b808",
        "chainId": "1"
      }
    ]
  },
  {
    "userId": "630619",
    "userAddress": "0x0058eea2c7bff1831bc9e0cd2647aee1ebfbd7b3",
    "profileDisplayName": "Gallivant07",
    "profileHandle": "gallivant07",
    "connectedAddresses": [
      {
        "address": "0xfda69ede4ceb4d5802c2f4a243727d3ba701883f",
        "chainId": "1"
      }
    ]
  },
  {
    "userId": "630620",
    "userAddress": "0x2233a585745406b45f8193536da013e6cd637a69",
    "profileDisplayName": "SandraJ72706940",
    "profileHandle": "sandraj72706940",
    "connectedAddresses": [
      {
        "address": "0xaf25cccb6d6b6a461937be48f4453c5886feaa69",
        "chainId": "1"
      }
    ]
  },
  {
    "userId": "630621",
    "userAddress": "0x1f2dfdc7d1cbb51f41c0a0a71983bc9d848893c1",
    "profileDisplayName": "Jose",
    "profileHandle": "2000annalisecuev",
    "connectedAddresses": [
      {
        "address": "0x8422531c6e16c6ea008a6667886012191cfdadc4",
        "chainId": "1"
      },
      {
        "address": "7QYzMhVPJQwxqKHkqYyFrgz5tXjmLCGjF4sR5qQCUxm2",
        "chainId": "900"
      }
    ]
  },
  {
    "userId": "630622",
    "userAddress": "0xc22bb41a02bfe679cc3d65d1666056f0ba3dd3ed",
    "profileDisplayName": "",
    "profileHandle": "profitable935",
    "connectedAddresses": []
  },
  {
    "userId": "630623",
    "userAddress": "0xda054dea7602f87eeb7cc7bc267246d198200f7c",
    "profileDisplayName": "Grace Green",
    "profileHandle": "robbiepeter",
    "connectedAddresses": [
      {
        "address": "4QcL49Zc4QpqAywJJCgfqawg6bZDWwaxmtQB1RFZ71Ja",
        "chainId": "900"
      },
      {
        "address": "0x7f624e3e69b8cd5a5e5e51711e5efbef4a05edcb",
        "chainId": "1"
      }
    ]
  },
  {
    "userId": "630624",
    "userAddress": "0xacd2fb51e9a15424f7a65fb0cfae2b5d87b06178",
    "profileDisplayName": "Molll",
    "profileHandle": "molll",
    "connectedAddresses": [
      {
        "address": "0xfce6f13e14d89c44948cb2d42f24c37dc82a2a3b",
        "chainId": "1"
      }
    ]
  },
  {
    "userId": "630625",
    "userAddress": "0x9c74845f543fb06daea1f624a7016e7d137cd58e",
    "profileDisplayName": "Hansen0",
    "profileHandle": "hansen0",
    "connectedAddresses": [
      {
        "address": "0x230f34d59c0cafb95af7365cf4e45ae8bc580705",
        "chainId": "1"
      }
    ]
  },
  {
    "userId": "630626",
    "userAddress": "0x9fded106fccb42ab5bec3399da39974f292ab759",
    "profileDisplayName": "Strongr",
    "profileHandle": "strongr",
    "connectedAddresses": [
      {
        "address": "0xcf86c268640030e376b277d46a08c8b46d3b9458",
        "chainId": "1"
      }
    ]
  },
  {
    "userId": "630627",
    "userAddress": "0xaf1bd92c58970e0d62cb2628038e086bf9efe9f5",
    "profileDisplayName": "dottyback",
    "profileHandle": "dottyback",
    "connectedAddresses": [
      {
        "address": "0xcb37ed1569a16333e3ae36c777179b2c984ec2cc",
        "chainId": "1"
      },
      {
        "address": "7nLYW51TBj5K68EYCTErp1ecNNjCQm9yWETXuiooWM5R",
        "chainId": "900"
      }
    ]
  },
  {
    "userId": "630628",
    "userAddress": "0xfc5c004006fd21e2fde71eef4b979d8766c12296",
    "profileDisplayName": "hshshah",
    "profileHandle": "jsbsaij",
    "connectedAddresses": [
      {
        "address": "0x1541a8de3ae9074333413262148edf28f0c10453",
        "chainId": "1"
      }
    ]
  },
  {
    "userId": "630629",
    "userAddress": "0x3f6021f0824910f4d7107251f6ef295b0a2fa9c2",
    "profileDisplayName": "PPG zhao",
    "profileHandle": "zzppg1",
    "connectedAddresses": []
  },
  {
    "userId": "630630",
    "userAddress": "0xe1b1a41e175d9c94943c466eb4bd4120a1ca52d7",
    "profileDisplayName": "d1a5d",
    "profileHandle": "d1a5d",
    "connectedAddresses": [
      {
        "address": "0xcef6deac4327c2cd6f28beaae6d6bcb1e9bd1a5d",
        "chainId": "1"
      },
      {
        "address": "3kNFg7nJPH8T9rhj97UFskqeDsvgj72KkPdytAjABiC2",
        "chainId": "900"
      }
    ]
  },
  {
    "userId": "630631",
    "userAddress": "0x4bae42e4dc719559656cb2ab72c1770d7237954f",
    "profileDisplayName": "Jshbsb",
    "profileHandle": "ghjk7",
    "connectedAddresses": [
      {
        "address": "0xf17e1776d2b006ccc00c9fcf861b0b0fc33db26e",
        "chainId": "1"
      }
    ]
  },
  {
    "userId": "630632",
    "userAddress": "0xd7461cc9743c8301135502c75eea54b93e393f98",
    "profileDisplayName": "doctor",
    "profileHandle": "doctorsexy",
    "connectedAddresses": [
      {
        "address": "0xa5bd0aff9e9f3fc269a5872c59fb69862f7e8e0c",
        "chainId": "1"
      },
      {
        "address": "AZyQ5KkRiTWrEgPEneDBRaaXrfjdnJccg4EDJs2qcadP",
        "chainId": "900"
      }
    ]
  },
  {
    "userId": "630633",
    "userAddress": "0xfcfff3ded5fe434ee46bea50d00cb6807646853c",
    "profileDisplayName": "Gavin Lillian秒回关注",
    "profileHandle": "zzq",
    "connectedAddresses": [
      {
        "address": "0x2c37192821ff618767e8b7fa356f005b02fe4d23",
        "chainId": "1"
      },
      {
        "address": "7UYS7fdMo6u3Laq1dk3XcyuaU7DY3qcMqPxo2do2cWd4",
        "chainId": "900"
      }
    ]
  },
  {
    "userId": "630634",
    "userAddress": "0x9923c27b094f615cbc0d165fdc751ef0b5eaf9a3",
    "profileDisplayName": "sadiyaray843",
    "profileHandle": "sadiyaray843",
    "connectedAddresses": [
      {
        "address": "0x0a6d3d9635784e16e382deb6dd88bf50d29e0b18",
        "chainId": "1"
      },
      {
        "address": "31Z7CdqGgxfUvtJZ9ZtzsEpfyP4bP8Xa7Ki6SDxhDirL",
        "chainId": "900"
      }
    ]
  },
  {
    "userId": "630635",
    "userAddress": "0xb985a10b59f70c105cb7a86004c5fea20fcdb496",
    "profileDisplayName": "rachellneal7981982",
    "profileHandle": "rachellneal753",
    "connectedAddresses": []
  },
  {
    "userId": "630636",
    "userAddress": "0xd2e083aaa26903bcfdc4d8ff46f84ed3c0204bf0",
    "profileDisplayName": "Laure",
    "profileHandle": "laure8",
    "connectedAddresses": [
      {
        "address": "0x1be957430a89c8e1e8a2d4038f4f499258c7eb51",
        "chainId": "1"
      }
    ]
  },
  {
    "userId": "630637",
    "userAddress": "0xc5ee7719b3ed1eb90dc754a31f69ca3735de51a6",
    "profileDisplayName": "loomer",
    "profileHandle": "loomer",
    "connectedAddresses": [
      {
        "address": "0x2d08dae47232c3fc00267a4b87fb7faed4aa3075",
        "chainId": "1"
      },
      {
        "address": "CdrA3wJNTHeVs5YiymQkG6rYPnVSLGCrCTfDsxvWVpTP",
        "chainId": "900"
      }
    ]
  },
  {
    "userId": "630638",
    "userAddress": "0xd262e27c3443c56425595126dba5ffc87fa6866b",
    "profileDisplayName": "Fhh",
    "profileHandle": "vhhh",
    "connectedAddresses": [
      {
        "address": "0xe102132e14ee83abe5488a2fd259e07234ec959d",
        "chainId": "1"
      }
    ]
  },
  {
    "userId": "630639",
    "userAddress": "0x52d6968d01d67a12249021e24f66377325c9e798",
    "profileDisplayName": "fv77",
    "profileHandle": "fv77",
    "connectedAddresses": [
      {
        "address": "0x91104720e70fb140a8542bd1f7752eb15f0b2235",
        "chainId": "1"
      }
    ]
  },
  {
    "userId": "630640",
    "userAddress": "0x079a9882d7bc24b9ff4e44c29875d218ed7e0ecc",
    "profileDisplayName": "vavaa",
    "profileHandle": "vavaa",
    "connectedAddresses": [
      {
        "address": "0xf9d59f0d6ebd542163ec3fb81df4e99263aa2fd2",
        "chainId": "1"
      }
    ]
  },
  {
    "userId": "630641",
    "userAddress": "0x06a200c0bc07b7071a02951a3e0430bee06f4184",
    "profileDisplayName": "WanderlustSoul",
    "profileHandle": "fisivjg",
    "connectedAddresses": [
      {
        "address": "0x66731cba5cef71d2ff12c8520c445d3d16878c61",
        "chainId": "1"
      }
    ]
  },
  {
    "userId": "630642",
    "userAddress": "0x8cd10c12aced89746514c73e01c91b8d835a884f",
    "profileDisplayName": "fredalandon",
    "profileHandle": "fredalandon",
    "connectedAddresses": [
      {
        "address": "0xf76cf0888bae9277b278573ef52cc7c33b5d3121",
        "chainId": "1"
      }
    ]
  },
  {
    "userId": "630643",
    "userAddress": "0xc95b50e60c96b355c282a0f839e071b5212c7745",
    "profileDisplayName": "Metalepsis",
    "profileHandle": "metalepsis",
    "connectedAddresses": [
      {
        "address": "0x3ebadbf8cde526713418dd808c0c4a861247bd50",
        "chainId": "1"
      }
    ]
  },
  {
    "userId": "630644",
    "userAddress": "0x52c2dfe191233a5df6040d794fcaf5f499e828bb",
    "profileDisplayName": "damsel",
    "profileHandle": "damsel",
    "connectedAddresses": [
      {
        "address": "0x255aa594fe2d1dae0debed1cf0a5f52e870faffa",
        "chainId": "1"
      },
      {
        "address": "DTs5G8e7y82JRVDA4pPTwHU6ogQ5tEPERMj16Bm1S29U",
        "chainId": "900"
      }
    ]
  },
  {
    "userId": "630645",
    "userAddress": "0xb6d34f8af828776e3fddc996066cf5221d849d51",
    "profileDisplayName": "Beautiful🥕 F4F🥕 互关",
    "profileHandle": "mingrenjj",
    "connectedAddresses": [
      {
        "address": "0x4d6d545f002a4a296af1f32d9248da75daf7f8fe",
        "chainId": "1"
      }
    ]
  },
  {
    "userId": "630646",
    "userAddress": "0x689335ef4719225029d0ce1f79b5afaed31b86ed",
    "profileDisplayName": "Ricky",
    "profileHandle": "rickyvanhee",
    "connectedAddresses": [
      {
        "address": "0x5ee80227ea748eb882497cbffcce0fad410b764c",
        "chainId": "1"
      }
    ]
  },
  {
    "userId": "630647",
    "userAddress": "0xef18e5e8120af08f8bc861b7109f3e528851dee0",
    "profileDisplayName": "5b04a",
    "profileHandle": "5b04a",
    "connectedAddresses": [
      {
        "address": "0xa2041adbb0e633b80484a23e625e40d72395b04a",
        "chainId": "1"
      },
      {
        "address": "GVLmMCfqqT8CPwApsvK3BvvEwDXu4gu4X3VnSzCKzcbS",
        "chainId": "900"
      }
    ]
  },
  {
    "userId": "630648",
    "userAddress": "0xcee0723cad0dea04c3e16f5ca6cd6d5dd240337d",
    "profileDisplayName": "Trevor",
    "profileHandle": "billymclean24",
    "connectedAddresses": [
      {
        "address": "0xba7e21cac28226575dc6816e811ec2a94e43c028",
        "chainId": "1"
      },
      {
        "address": "2zm17AhS5gcBwRYhXnPhFT3p4TaEUraHL3bMVgFzvDbf",
        "chainId": "900"
      }
    ]
  },
  {
    "userId": "630649",
    "userAddress": "0xf8146f97abed72f92f68963bf7acc124ec62c69d",
    "profileDisplayName": "Syed 🎭 ",
    "profileHandle": "ikens",
    "connectedAddresses": []
  },
  {
    "userId": "630650",
    "userAddress": "0x568474569217623a3673c8db29d859299f418070",
    "profileDisplayName": "pistachion",
    "profileHandle": "pistachion",
    "connectedAddresses": [
      {
        "address": "0x73dcae90aefc927df065146823be7ea88157aa16",
        "chainId": "1"
      }
    ]
  },
  {
    "userId": "630651",
    "userAddress": "0x418860025ad446becfba3f174d6394a20ed7f799",
    "profileDisplayName": "Abiodun BOSEDE",
    "profileHandle": "olaslove",
    "connectedAddresses": []
  },
  {
    "userId": "630652",
    "userAddress": "0xd0174361cfc3792d10479b28d5ac45338b35bdbc",
    "profileDisplayName": "Олексій",
    "profileHandle": "alex277",
    "connectedAddresses": [
      {
        "address": "0xa34059142524b273145638d3ec8d0dcb59e8b5f7",
        "chainId": "1"
      },
      {
        "address": "JD662cuoGuqEUkm532u1ig67eTDwzhHNFLCMGb5qmQGg",
        "chainId": "900"
      }
    ]
  },
  {
    "userId": "630653",
    "userAddress": "0xe8272d5515fb5af9174a0c29423ec6dbd2422d01",
    "profileDisplayName": "rabbitfish",
    "profileHandle": "rabbitfish",
    "connectedAddresses": [
      {
        "address": "0xb5203e428405218a97383e762ac6fbe27a2f6411",
        "chainId": "1"
      },
      {
        "address": "H3FUGpP2SA9dps8M8Pd8XApD8uCqvKouWFvWT8dQDZFR",
        "chainId": "900"
      }
    ]
  },
  {
    "userId": "630654",
    "userAddress": "0x36c93c8b838da8e9fb9ac24712d19ed5198712b4",
    "profileDisplayName": "Evan",
    "profileHandle": "evan77",
    "connectedAddresses": [
      {
        "address": "0x999b1640293da987d903891f910127fd5d51ffd4",
        "chainId": "1"
      },
      {
        "address": "DtVNgwGD7AM3dyDF2qsVAK9tdrJgk8gfnHkFrVqJXwLw",
        "chainId": "900"
      }
    ]
  },
  {
    "userId": "630655",
    "userAddress": "0x6fdbf4aa2ccace1d0e8594b23c4e657f2bb529e4",
    "profileDisplayName": "zhangfang3",
    "profileHandle": "zhangfang3",
    "connectedAddresses": [
      {
        "address": "0x58c9bd5d65da224a9a111d3c83fa144d81f9b612",
        "chainId": "1"
      }
    ]
  },
  {
    "userId": "630656",
    "userAddress": "0x737868d393c2d6a59180917d68869630d3c07240",
    "profileDisplayName": "3ffc",
    "profileHandle": "3ffc",
    "connectedAddresses": [
      {
        "address": "0x01e340ca6bda9ca766fdbfa2082f9b30eb8d5499",
        "chainId": "1"
      }
    ]
  },
  {
    "userId": "630657",
    "userAddress": "0xdf1ff4e74c8cf933181e8e6e5ac21d1302961d09",
    "profileDisplayName": "Kevin",
    "profileHandle": "amandachaney11",
    "connectedAddresses": [
      {
        "address": "0x4dc647107962752d2dde4f2b8f023c1955af1dc0",
        "chainId": "1"
      },
      {
        "address": "AzDtcrXd3oLq853RCM5FPN3n1JUVrZRERskbKhhkA9YN",
        "chainId": "900"
      }
    ]
  },
  {
    "userId": "630658",
    "userAddress": "0x221f58eeed2a22f1529b15e27e3d0cb3c242a115",
    "profileDisplayName": "Grudgemental",
    "profileHandle": "grudgemental",
    "connectedAddresses": [
      {
        "address": "0xb035a9b756b43292890cc1ac24e61ff8e4455550",
        "chainId": "1"
      }
    ]
  },
  {
    "userId": "630659",
    "userAddress": "0x145be1d488bef886c25f6f85a72348d397ad0ef2",
    "profileDisplayName": "Abctwo",
    "profileHandle": "abctwo88",
    "connectedAddresses": [
      {
        "address": "0x12ff2cb07c2a8cfb7804bc045e1e421a8285d448",
        "chainId": "1"
      },
      {
        "address": "2xWJmDCgcUmDekDRqcSJiw9xRybXCMf3hbRZKQwv6fMy",
        "chainId": "900"
      }
    ]
  },
  {
    "userId": "630660",
    "userAddress": "0x06dfc5c729920d744307b3c6bea2af078f0187cc",
    "profileDisplayName": "Felicia Putri ",
    "profileHandle": "felicailputrifx",
    "connectedAddresses": []
  },
  {
    "userId": "630661",
    "userAddress": "0xf749e8a295fcd231d6450c2fbbe79c32c913a526",
    "profileDisplayName": "quetajuarez7487",
    "profileHandle": "kibuntin5",
    "connectedAddresses": []
  },
  {
    "userId": "630662",
    "userAddress": "0x505894fda8675666d22ff4030feacc3bf3ccf82e",
    "profileDisplayName": "Ikhizama_jr",
    "profileHandle": "ikhizama24",
    "connectedAddresses": []
  },
  {
    "userId": "630663",
    "userAddress": "0x55af2126aba66107a49e073cd09a4f7d132d5b39",
    "profileDisplayName": "kibuntin",
    "profileHandle": "quetajuarez7487",
    "connectedAddresses": []
  },
  {
    "userId": "630664",
    "userAddress": "0xe6f93e1a73c3c3abb074e9aee309a4607a6d181e",
    "profileDisplayName": "Caprikole",
    "profileHandle": "caprikole",
    "connectedAddresses": []
  },
  {
    "userId": "630665",
    "userAddress": "0xfd50e8af41168856fd609b0c7f34b3ae137c433b",
    "profileDisplayName": "EvenEdgy",
    "profileHandle": "bledtwit",
    "connectedAddresses": [
      {
        "address": "0x3f5515c5349cc2cfa0b8ca33cec840fdf64ca5d4",
        "chainId": "1"
      },
      {
        "address": "C19EeRzAMpbQa2T6kNU798iMBWSLwEuSP5tTyEdCRSdV",
        "chainId": "900"
      }
    ]
  },
  {
    "userId": "630666",
    "userAddress": "0x51e00358cd318e6b391bfd46f38bea81e5b533a5",
    "profileDisplayName": "Genesic",
    "profileHandle": "genesic",
    "connectedAddresses": [
      {
        "address": "0x14a1cae4702a7c3389d086cf59b4888ed7590293",
        "chainId": "1"
      }
    ]
  },
  {
    "userId": "630667",
    "userAddress": "0xc617dfaf82b2a299d3041c227a28ec6ec3d32128",
    "profileDisplayName": "yuyyki",
    "profileHandle": "yuyyki",
    "connectedAddresses": [
      {
        "address": "0xc7cce98b462fb89ade3d716700e840eed403f1ca",
        "chainId": "1"
      }
    ]
  },
  {
    "userId": "630668",
    "userAddress": "0x9c37cc05ecd049e1a13dcbf7fa59cefc23d273c4",
    "profileDisplayName": "surgeon",
    "profileHandle": "surgeon",
    "connectedAddresses": [
      {
        "address": "0x2397944d8fdd515cb498282acd76e4c2721d36aa",
        "chainId": "1"
      },
      {
        "address": "FzWRsPBEJvD9gNfs97QHrux1yz9At7FG6D9QpT5fG7Rh",
        "chainId": "900"
      }
    ]
  },
  {
    "userId": "630669",
    "userAddress": "0xcda1da74270a3537f1cafdddd249305212682d08",
    "profileDisplayName": "Dmitriy",
    "profileHandle": "lelantos0001",
    "connectedAddresses": []
  },
  {
    "userId": "630670",
    "userAddress": "0x3b9f05572d2fbcdcd669481f1ce4547b351cdbb6",
    "profileDisplayName": "okn互相关注",
    "profileHandle": "okn",
    "connectedAddresses": [
      {
        "address": "0xd4b34cecb16f081f4516b13ff889c0d010654ce7",
        "chainId": "1"
      },
      {
        "address": "HaUKut2sJG4qh1qisbnFD3vNK83hX2tuq47omsuCbMKx",
        "chainId": "900"
      }
    ]
  },
  {
    "userId": "630671",
    "userAddress": "0xb348424592aed9ef9cd491b74f03811ce85c383f",
    "profileDisplayName": "Spitstrle",
    "profileHandle": "spitstrle",
    "connectedAddresses": [
      {
        "address": "0xd4c2a97c75b27bc8dc86a0a8174e868b8572dacf",
        "chainId": "1"
      }
    ]
  },
  {
    "userId": "630672",
    "userAddress": "0xc223af77d963ed14a1634b7ff5e231c2ace008a4",
    "profileDisplayName": "",
    "profileHandle": "tough801",
    "connectedAddresses": [
      {
        "address": "0xc223af77d963ed14a1634b7ff5e231c2ace008a4",
        "chainId": "1"
      }
    ]
  },
  {
    "userId": "630673",
    "userAddress": "0xf1700b84145d77026377d0667f29e2ace1c9c5d3",
    "profileDisplayName": "Andy Key",
    "profileHandle": "8goldenboy8",
    "connectedAddresses": [
      {
        "address": "0x241994b83e4d34eeb7c0edacd341ace5e5aa324c",
        "chainId": "1"
      }
    ]
  },
  {
    "userId": "630674",
    "userAddress": "0x67ff46cd90df341bc3a5152fcd13bc46a27dac9c",
    "profileDisplayName": "noahhala",
    "profileHandle": "noahhaladtkeull",
    "connectedAddresses": [
      {
        "address": "0x68260a52ea7628ebc472d32bea7286b0d7e83b83",
        "chainId": "1"
      }
    ]
  },
  {
    "userId": "630675",
    "userAddress": "0xbc694341ab66fac04dd69038b7e601c9bab99a8d",
    "profileDisplayName": "Shaheen",
    "profileHandle": "shaheenislam",
    "connectedAddresses": []
  },
  {
    "userId": "630676",
    "userAddress": "0x3e03d3b1039d06a699f2148421831f4a63811478",
    "profileDisplayName": "James Bowman",
    "profileHandle": "forw",
    "connectedAddresses": [
      {
        "address": "0x9f105f50cf23c10b6a53ba99b217a6c9d3ec193f",
        "chainId": "1"
      }
    ]
  },
  {
    "userId": "630677",
    "userAddress": "0xe7fb9cd2e50d977ffcb9ae979e6dce57d4578de7",
    "profileDisplayName": "fff4",
    "profileHandle": "ksnmdpz",
    "connectedAddresses": [
      {
        "address": "0xc0cf9710fa370985e847817d0080863418634176",
        "chainId": "1"
      }
    ]
  },
  {
    "userId": "630678",
    "userAddress": "0x0469c3045960f76549eab2bd609d16fc114fd11a",
    "profileDisplayName": "Cameron",
    "profileHandle": "karlilowery12",
    "connectedAddresses": [
      {
        "address": "0x47a628d0a167dc5cbd43f3ac1f171a51a67e2d80",
        "chainId": "1"
      },
      {
        "address": "aZEKWbzk1ta6ykSQ1myMpeJX8LgtvGQhFY24o7kDWHq",
        "chainId": "900"
      }
    ]
  },
  {
    "userId": "630679",
    "userAddress": "0x9a7880f6c4eab0be3b2a597b8fc1a37bc081bb6f",
    "profileDisplayName": "arkell",
    "profileHandle": "arkell",
    "connectedAddresses": []
  },
  {
    "userId": "630680",
    "userAddress": "0x66a890a478b3fcabdcea93bb28768fa4c3217b32",
    "profileDisplayName": "Mark Goldbridge",
    "profileHandle": "markgoldbridge",
    "connectedAddresses": [
      {
        "address": "0x2e8521667d84caa6a54c7c6f7d34bfb7d511ddb3",
        "chainId": "1"
      },
      {
        "address": "9cS32s3kTPDAgWHbw4gHG54NvBEHvK9SYjJ5DzmHubZf",
        "chainId": "900"
      }
    ]
  },
  {
    "userId": "630681",
    "userAddress": "0xf017c02d8d6cfd471d398ac47e2394985b911054",
    "profileDisplayName": "parrotfisho",
    "profileHandle": "parrotfisho",
    "connectedAddresses": [
      {
        "address": "0x18328af22d8b84c78a41a7bbd865e50d43510a4a",
        "chainId": "1"
      },
      {
        "address": "J6XSmD6LfaRpbQANB2x5tsqcoaqJrjsehpbwpbdbMnVe",
        "chainId": "900"
      }
    ]
  },
  {
    "userId": "630682",
    "userAddress": "0x68097b02ce4e49e6751daf057e12b188233cf38f",
    "profileDisplayName": "Marvel oghonyon",
    "profileHandle": "tentaclesmarv",
    "connectedAddresses": []
  },
  {
    "userId": "630683",
    "userAddress": "0x9a6abd45b81b93ed60d155440e14eef9bd7a7143",
    "profileDisplayName": "Eric",
    "profileHandle": "piercehelena25",
    "connectedAddresses": [
      {
        "address": "0x863f1b3f89e5d484af5f644aacbca6d673095597",
        "chainId": "1"
      },
      {
        "address": "9FXL8GVxUx9J3y9nT9DBYGC53bfrfgFZhHQVf1vB5yNi",
        "chainId": "900"
      }
    ]
  },
  {
    "userId": "630684",
    "userAddress": "0x0de03c8a89ebd0f6f76f45bf44d8a53661a2ea42",
    "profileDisplayName": "rnondini12",
    "profileHandle": "rnondini12",
    "connectedAddresses": [
      {
        "address": "0xa0d85512b28b0737ffbc0ce1de48ca3c43369541",
        "chainId": "1"
      },
      {
        "address": "9tEBg5AtQBBvXMryLw3ofbRxwymY5FvmK67jBXGHkb3j",
        "chainId": "900"
      }
    ]
  },
  {
    "userId": "630685",
    "userAddress": "0x1501d4bbe229134bbe48c078a11bbced3e12d646",
    "profileDisplayName": "eltonmieltonmitsue",
    "profileHandle": "eltonmieltonmitl",
    "connectedAddresses": []
  },
  {
    "userId": "630686",
    "userAddress": "0x7006c4afa1a419e3b9b63ed4e6d16dd82055f901",
    "profileDisplayName": "Allan Jay Soria",
    "profileHandle": "1terabyt3",
    "connectedAddresses": []
  },
  {
    "userId": "630687",
    "userAddress": "0x1fe0892e70812654016bbda0de51d7d54522276f",
    "profileDisplayName": "Praepostor",
    "profileHandle": "praepostor",
    "connectedAddresses": [
      {
        "address": "0xef64250b0ad1edf334785e3e578fe5e193f6ce16",
        "chainId": "1"
      }
    ]
  },
  {
    "userId": "630688",
    "userAddress": "0xed1f028a7eb487c8a19ed5bf93477e89e182cb04",
    "profileDisplayName": "degen",
    "profileHandle": "degen-mode",
    "connectedAddresses": [
      {
        "address": "0x004057e952a59eea511a80520a40f467bdd536a0",
        "chainId": "1"
      }
    ]
  },
  {
    "userId": "630689",
    "userAddress": "0xcd57d7a46932a11df37e6a55ffaef1baa239295c",
    "profileDisplayName": "Benedikt -",
    "profileHandle": "vinette",
    "connectedAddresses": [
      {
        "address": "0xb834ac3f0d4da03c5d4e2146a0b50aea209f4fb1",
        "chainId": "1"
      }
    ]
  },
  {
    "userId": "630690",
    "userAddress": "0x9620ff14c48b3b88e170323e2b4087c5435ee635",
    "profileDisplayName": "sol",
    "profileHandle": "solp",
    "connectedAddresses": [
      {
        "address": "0xc3692a37ab996f90c24f1ebf88c1dd503bb00624",
        "chainId": "1"
      }
    ]
  },
  {
    "userId": "630691",
    "userAddress": "0xc96a75ae4c491633df2d934cc0723199f1493e6f",
    "profileDisplayName": "wrassek",
    "profileHandle": "wrassek",
    "connectedAddresses": [
      {
        "address": "0x4eebc5a9b6f14fc226489b7c6ffec84728048f80",
        "chainId": "1"
      },
      {
        "address": "8t3z4MVbNV2kwTBerfqHWxmeXpzca38mP48GiiUXuTHN",
        "chainId": "900"
      }
    ]
  },
  {
    "userId": "630692",
    "userAddress": "0xc7e41c7b34a351f30ea09275a643ef2c6d747074",
    "profileDisplayName": "kikim",
    "profileHandle": "kikim",
    "connectedAddresses": [
      {
        "address": "0x1e5f52255cab297cc36e2043a62f27f12a5750fb",
        "chainId": "1"
      }
    ]
  },
  {
    "userId": "630693",
    "userAddress": "0x632559e134db791cbd1eb16b5dbfbce65b87624d",
    "profileDisplayName": "Mirza Abdullah",
    "profileHandle": "hotstolen",
    "connectedAddresses": []
  },
  {
    "userId": "630694",
    "userAddress": "0x7103fdb658da15b52000cbdab30b196878b30646",
    "profileDisplayName": "🤞𝓡𝓸𝓷𝓪𝓵𝓭",
    "profileHandle": "riaminoz",
    "connectedAddresses": []
  },
  {
    "userId": "630695",
    "userAddress": "0xa104a3f15b57dc0509c3383fb211d47abbe1f7a5",
    "profileDisplayName": "margueritelew",
    "profileHandle": "margueritelew",
    "connectedAddresses": [
      {
        "address": "0x9ce9ef42f6275313a83373fa4d0ca2a663411c1d",
        "chainId": "1"
      }
    ]
  },
  {
    "userId": "630696",
    "userAddress": "0x816397284bdc3123fae59ada0df8a14870ae5964",
    "profileDisplayName": "big blaise",
    "profileHandle": "bigblaise",
    "connectedAddresses": []
  },
  {
    "userId": "630697",
    "userAddress": "0x220cdce102f418ea6a29501f6991e4abdabcff6f",
    "profileDisplayName": "CodingKenta",
    "profileHandle": "coding-kenta",
    "connectedAddresses": []
  },
  {
    "userId": "630698",
    "userAddress": "0xe0cf6ad8f3ca48304c13f350b85a2363e22cf211",
    "profileDisplayName": "Marie Olivier",
    "profileHandle": "marieolivier",
    "connectedAddresses": [
      {
        "address": "0x345122f87eeeb2bfaf20f21dfc40cf06a685798a",
        "chainId": "1"
      }
    ]
  },
  {
    "userId": "630699",
    "userAddress": "0x758c3df8fa1ffd2df811a897529d6789f2bbfc5c",
    "profileDisplayName": "Serdar",
    "profileHandle": "lacantina",
    "connectedAddresses": []
  },
  {
    "userId": "630700",
    "userAddress": "0x86c2613190808690a7eaab01250051be25bea709",
    "profileDisplayName": "Syed Saffi",
    "profileHandle": "syed02",
    "connectedAddresses": []
  },
  {
    "userId": "630701",
    "userAddress": "0x45295c6a74173979085519cd1f1ee0f110b05fc7",
    "profileDisplayName": "Curlicue",
    "profileHandle": "curlicue",
    "connectedAddresses": [
      {
        "address": "0x3f34823fcfa45c3217ddd577d366c0e5d8d9d259",
        "chainId": "1"
      }
    ]
  },
  {
    "userId": "630702",
    "userAddress": "0xfcd2e99babdede5cd9dec150fe68a6cd99606224",
    "profileDisplayName": "MosKubpom",
    "profileHandle": "moskubpom",
    "connectedAddresses": [
      {
        "address": "0x922b38449e17eef7bde8152c0168e8bbb43cb429",
        "chainId": "1"
      }
    ]
  },
  {
    "userId": "630703",
    "userAddress": "0xff3cd819e73f5894b4496dbae5e02167746b7cb6",
    "profileDisplayName": "Okike israelphilips",
    "profileHandle": "okike",
    "connectedAddresses": []
  },
  {
    "userId": "630704",
    "userAddress": "0x4b7bbb306a19dac7992a67ba6cf349507110fa8b",
    "profileDisplayName": "Bsbbs",
    "profileHandle": "bcfjg888",
    "connectedAddresses": [
      {
        "address": "0xade15d83c29a424d5d25661bd67ec4a62df91195",
        "chainId": "1"
      }
    ]
  },
  {
    "userId": "630705",
    "userAddress": "0xbfde75974d5d2c78cdc6bf0802a877f13ddf4ba7",
    "profileDisplayName": "Nova Quasar",
    "profileHandle": "novato",
    "connectedAddresses": [
      {
        "address": "0x7af68e2199889d39bc361c616809bbd934f0de94",
        "chainId": "1"
      },
      {
        "address": "8AKparByQBQJ7qqohG9v6V7Zyu7jYPMJce8tnomZme5E",
        "chainId": "900"
      }
    ]
  },
  {
    "userId": "630706",
    "userAddress": "0xa4fc76d149226e49e309ee8fc8c4e2d62079bc11",
    "profileDisplayName": "Timothy",
    "profileHandle": "joe1999drake",
    "connectedAddresses": [
      {
        "address": "0x88b8f74369ae79bab27e5e28a95c81daec22d514",
        "chainId": "1"
      },
      {
        "address": "GCZuEhXATPczDaskHXz9Pt9g9xiAkkBb1FKS72P9tmqk",
        "chainId": "900"
      }
    ]
  },
  {
    "userId": "630707",
    "userAddress": "0x056862b62503ba09724477406104f637a9532b31",
    "profileDisplayName": "Anuoluwapo Owolabi",
    "profileHandle": "gb02",
    "connectedAddresses": []
  },
  {
    "userId": "630708",
    "userAddress": "0xe89737f479d559f4002ecd01b226b0119cf323da",
    "profileDisplayName": "",
    "profileHandle": "amayafullm6",
    "connectedAddresses": []
  },
  {
    "userId": "630709",
    "userAddress": "0x9e1d3c1ef740e2b2538ad7a873629c7eaa88fb47",
    "profileDisplayName": "rujinaray647",
    "profileHandle": "rujinaray647",
    "connectedAddresses": [
      {
        "address": "0x56e2771194b91e635592d2a303bc25320cc20778",
        "chainId": "1"
      },
      {
        "address": "HpXqXMUKfMmncCfvTQ1yJyF52WtAjXiJ7NivGpRTaNdp",
        "chainId": "900"
      }
    ]
  },
  {
    "userId": "630710",
    "userAddress": "0x6b6978a6ce7bf5e45207f22bb0753f5e7e64e5f5",
    "profileDisplayName": "sweetlips",
    "profileHandle": "sweetlips",
    "connectedAddresses": [
      {
        "address": "0x96df1e136bab5d734afaa55e9e3d53fe6c2d59d6",
        "chainId": "1"
      },
      {
        "address": "Ar66UVqJwNuR4h5QRym1Y2wxdbJbXCGZ4SoLffNzBpDS",
        "chainId": "900"
      }
    ]
  },
  {
    "userId": "630711",
    "userAddress": "0x1c3442085ea7c7738c72466664d98ee666ce8d9d",
    "profileDisplayName": "Defi Focus",
    "profileHandle": "defifocus",
    "connectedAddresses": []
  },
  {
    "userId": "630712",
    "userAddress": "0x96fb58753f650698a76e601774fc87f12bb223d4",
    "profileDisplayName": "Johnson4",
    "profileHandle": "johnson4",
    "connectedAddresses": [
      {
        "address": "0x238fe6e2a7c33acbb9b3c8999c759cb0f70bff18",
        "chainId": "1"
      }
    ]
  },
  {
    "userId": "630713",
    "userAddress": "0x6d4ba9c004a2a25497cf51c7de5c08378d303755",
    "profileDisplayName": "Fernando",
    "profileHandle": "27gouldleia",
    "connectedAddresses": [
      {
        "address": "0x99db9b971bacc197a65999f4840091fda35ad1fe",
        "chainId": "1"
      },
      {
        "address": "DFDYkb7ibzhcwMz9xSp2boJzRQ2nC5iYWW1EU4MocfYW",
        "chainId": "900"
      }
    ]
  },
  {
    "userId": "630714",
    "userAddress": "0x87077bab974230ce800e5f9b65b7edd9163508f6",
    "profileDisplayName": "Brown78",
    "profileHandle": "brown78",
    "connectedAddresses": [
      {
        "address": "0x7c29378db26376f70c411f02e63df2909df1612f",
        "chainId": "1"
      }
    ]
  },
  {
    "userId": "630715",
    "userAddress": "0x69242c2aa8e93fd22177b8adea8a6d385f3cb22f",
    "profileDisplayName": "sanqian",
    "profileHandle": "sanqian2024",
    "connectedAddresses": [
      {
        "address": "0xdf8898223854e4087dad667221d2844e816eac95",
        "chainId": "1"
      }
    ]
  },
  {
    "userId": "630716",
    "userAddress": "0xd1ce72fc79273585b6baa2b66d29f8f7d03dc15d",
    "profileDisplayName": "MarkSavagin",
    "profileHandle": "marksavagin",
    "connectedAddresses": [
      {
        "address": "0x229fbe560b2b6e022e0f0bd0aa9cbeb7eb5196ed",
        "chainId": "1"
      },
      {
        "address": "5uH3MwuDwCGYhhLAtUAUFc71qBh6ujCKZLMXwuHV6Jsa",
        "chainId": "900"
      }
    ]
  },
  {
    "userId": "630717",
    "userAddress": "0xeeb685cb4531b4b46f830afabe9bdebcceb3f792",
    "profileDisplayName": "c0a62",
    "profileHandle": "c0a62",
    "connectedAddresses": [
      {
        "address": "0x09f85aca1daf80a2cee338b9ac6e7f478b9c0a62",
        "chainId": "1"
      },
      {
        "address": "9rHZbUK1t3h5GkSTMJqxZoh2RyRpBksqpPpwwoeP2hBP",
        "chainId": "900"
      }
    ]
  },
  {
    "userId": "630718",
    "userAddress": "0x4115f58f2be595c2e45eb186959a7e656a988ded",
    "profileDisplayName": "Natik",
    "profileHandle": "natanata",
    "connectedAddresses": [
      {
        "address": "0x71658afea0b3d3e5107929cb466636e42d48d3b1",
        "chainId": "1"
      }
    ]
  },
  {
    "userId": "630719",
    "userAddress": "0x1b889e4faef537a9d82b7f55719fc497f3ab3d84",
    "profileDisplayName": "Dmitriy Sidorenko",
    "profileHandle": "cockroach0808",
    "connectedAddresses": []
  },
  {
    "userId": "630720",
    "userAddress": "0x7adc6de9d8d306ba120a6122181984b8f9d916d4",
    "profileDisplayName": "dbbn",
    "profileHandle": "dbbn",
    "connectedAddresses": [
      {
        "address": "0x1cfd2d66cbb8227d5d5c2dc5fb095622d3ba4f8a",
        "chainId": "1"
      }
    ]
  },
  {
    "userId": "630721",
    "userAddress": "0xb06a7bdf1babc2e3d19aa986a768c2a8b9ff3aaf",
    "profileDisplayName": "Ronnie",
    "profileHandle": "ronniethedev",
    "connectedAddresses": [
      {
        "address": "0xb06a7bdf1babc2e3d19aa986a768c2a8b9ff3aaf",
        "chainId": "1"
      }
    ]
  },
  {
    "userId": "630722",
    "userAddress": "0xcdad143d6571a4b34cf4f68682398204016c9f3a",
    "profileDisplayName": "butterflyfi",
    "profileHandle": "butterflyfi",
    "connectedAddresses": [
      {
        "address": "0xa9b44e8159e5709636d0f3fc7729da71007caecc",
        "chainId": "1"
      },
      {
        "address": "5Hwy96PjbzMRB3upmyPiET3QKLML7dukeNoSo5YcqL6r",
        "chainId": "900"
      }
    ]
  },
  {
    "userId": "630723",
    "userAddress": "0xab833f340bac2f039ef98821854335236e23c05d",
    "profileDisplayName": "Allife ",
    "profileHandle": "ailife",
    "connectedAddresses": [
      {
        "address": "0xab833f340bac2f039ef98821854335236e23c05d",
        "chainId": "1"
      }
    ]
  },
  {
    "userId": "630724",
    "userAddress": "0x57e001a9358ec2009bce11f5fc8f7dcb4291f1e4",
    "profileDisplayName": "",
    "profileHandle": "attractive734",
    "connectedAddresses": []
  },
  {
    "userId": "630725",
    "userAddress": "0x17c27f51d27d0546b7b9c9cbddccc952a0af0bc6",
    "profileDisplayName": "timio",
    "profileHandle": "timio",
    "connectedAddresses": [
      {
        "address": "0x58c5eb10a8e569d67751b18b912be0722022053c",
        "chainId": "1"
      }
    ]
  },
  {
    "userId": "630726",
    "userAddress": "0xe1f2575d1da96268528a5e4d2a3fa644dd074c4b",
    "profileDisplayName": "rressy298",
    "profileHandle": "rressy298",
    "connectedAddresses": [
      {
        "address": "0xd949d9bce08b2a95adcd852023f062073cb4f314",
        "chainId": "1"
      },
      {
        "address": "FxUtMf43R5HndPqjwnsH3SyhLabfXQ7qmU9F9PMZ3Ec1",
        "chainId": "900"
      }
    ]
  },
  {
    "userId": "630727",
    "userAddress": "0x29d9b70d39f7acb2a3943ed9a46cd8cf9a5b4a66",
    "profileDisplayName": "Bastiaen",
    "profileHandle": "usoniev",
    "connectedAddresses": [
      {
        "address": "0x14f4b2fea21e5b49e58461be7cb2c8c7628b4520",
        "chainId": "1"
      }
    ]
  },
  {
    "userId": "630728",
    "userAddress": "0x5d871bb6f43a492956ec1892f1a48a66771cf311",
    "profileDisplayName": "orvillenichol",
    "profileHandle": "orvillenichol",
    "connectedAddresses": [
      {
        "address": "0x805c94eccd12d9ed6fb0c6d98d2bb2552b089199",
        "chainId": "1"
      }
    ]
  },
  {
    "userId": "630729",
    "userAddress": "0x326eb71d4ea4040d60bbbda25a89e08ebc75ff35",
    "profileDisplayName": "Kale Soup",
    "profileHandle": "oftenfrequent",
    "connectedAddresses": []
  },
  {
    "userId": "630730",
    "userAddress": "0xcd585a1b105f9a86abe7e79e0347b8f86bc2542a",
    "profileDisplayName": "azurag",
    "profileHandle": "azurag",
    "connectedAddresses": [
      {
        "address": "0xc33323a59873f6cc24217a40532559906197f500",
        "chainId": "1"
      },
      {
        "address": "79dq3GEhyCK8LDu6AweUT7Xu3RvDxTsyaPcx9wLf8NSE",
        "chainId": "900"
      }
    ]
  },
  {
    "userId": "630731",
    "userAddress": "0x76a42eb02072901e2118dc07ffacbbc255acf9eb",
    "profileDisplayName": "MrBmacc",
    "profileHandle": "mrbmacc",
    "connectedAddresses": []
  },
  {
    "userId": "630732",
    "userAddress": "0x9d159e144c793b95278c9f172c576ca5b99dd874",
    "profileDisplayName": "Obiamaka Chioma Charles",
    "profileHandle": "chiomao",
    "connectedAddresses": []
  },
  {
    "userId": "630733",
    "userAddress": "0xf774cfc6bf7bcd682f17d89922c0928eef344490",
    "profileDisplayName": "ijgffghj",
    "profileHandle": "vvhjb",
    "connectedAddresses": [
      {
        "address": "0x0f081ca48732c440e80f42c3717950b13ce2e193",
        "chainId": "1"
      }
    ]
  },
  {
    "userId": "630734",
    "userAddress": "0xd4f061f43f6b87d53a80415369b95210f4f15db8",
    "profileDisplayName": "DENIS PAVLOVSKY",
    "profileHandle": "denisegg",
    "connectedAddresses": [
      {
        "address": "0xaf659fedabe208cb318d4316579a2191e9f46175",
        "chainId": "1"
      },
      {
        "address": "0x2eda7214978798c8c9cad6069f7233af37535856",
        "chainId": "1"
      }
    ]
  },
  {
    "userId": "630735",
    "userAddress": "0x910db45ea9c9bbfdf65f556c65f9d115453373b5",
    "profileDisplayName": "ftppzjk500",
    "profileHandle": "ftppzjk500",
    "connectedAddresses": [
      {
        "address": "0xa1eba305d3bd51ddf55fd2f038f0e8262f940e99",
        "chainId": "1"
      }
    ]
  },
  {
    "userId": "630736",
    "userAddress": "0x86f43404066fc90c2bc22fa86c48ac964e5908e3",
    "profileDisplayName": "Jivelw",
    "profileHandle": "chuchukivan",
    "connectedAddresses": [
      {
        "address": "0xd8a082fc137d44f8c0240801109e4c0399b6a693",
        "chainId": "1"
      },
      {
        "address": "CjwyW39vQ5UL6VRcyeHUnBsxdVwWyddSQ212A5Y41dRA",
        "chainId": "900"
      }
    ]
  },
  {
    "userId": "630737",
    "userAddress": "0xc0be3f9efddf06604cf05df44df410e4262227c3",
    "profileDisplayName": "Rebecca",
    "profileHandle": "salazarcory07",
    "connectedAddresses": [
      {
        "address": "0x51ffeeea2d9d2bd9d139b9888909399b42295b0d",
        "chainId": "1"
      },
      {
        "address": "97r2j6YaG6gLsCcdCaS39QwSD1wi2nm8LvNmGRvGwfp3",
        "chainId": "900"
      }
    ]
  },
  {
    "userId": "630738",
    "userAddress": "0x74a3cd566dcb012faf099e440f98e31e79d5bb1e",
    "profileDisplayName": "xenavine8030",
    "profileHandle": "xenavine3030",
    "connectedAddresses": []
  },
  {
    "userId": "630739",
    "userAddress": "0xbbec9a128fe1952119177cd30ef2607f15a9cb76",
    "profileDisplayName": "vjb",
    "profileHandle": "vjb",
    "connectedAddresses": [
      {
        "address": "0x7f0f0d372aa37c20b443c39d2cdb68d154ac19dd",
        "chainId": "1"
      },
      {
        "address": "9TrU7qeKQ1riZ2fLf8eVSZbRma9iXJoJYwLNYX67Y9eJ",
        "chainId": "900"
      }
    ]
  },
  {
    "userId": "630740",
    "userAddress": "0x5fc7b53f55a1e0ac2d748ae21f13fe1989c659fc",
    "profileDisplayName": "kakku",
    "profileHandle": "kakku",
    "connectedAddresses": [
      {
        "address": "0xffa2f2cc9e4add8e33410c78dd163ba9a87ce2c9",
        "chainId": "1"
      },
      {
        "address": "7VaYsviaMuK7nUBNeAXNDRSvz3MurtZqHPvrXpJqjVnz",
        "chainId": "900"
      }
    ]
  },
  {
    "userId": "630741",
    "userAddress": "0x666b1af09d8692a2850eb36d9654e718ed0ae483",
    "profileDisplayName": "kairosb",
    "profileHandle": "kairosb",
    "connectedAddresses": [
      {
        "address": "0x34f964b96f08187d6eb4fe33ca94c535059c6f1f",
        "chainId": "1"
      },
      {
        "address": "Ee3jA8hPtrENvj9DSYbe4mTddkMknqazJSFRuRfhAPau",
        "chainId": "900"
      }
    ]
  },
  {
    "userId": "630742",
    "userAddress": "0x31b0bb3edc3b1c2d739e0b84d076ff6b0e7b38e1",
    "profileDisplayName": "Minzilya",
    "profileHandle": "karimova",
    "connectedAddresses": []
  },
  {
    "userId": "630743",
    "userAddress": "0x4aff60b1c330b83c9f92efffdd5e7df9f5c69858",
    "profileDisplayName": "Lesia",
    "profileHandle": "lesia",
    "connectedAddresses": [
      {
        "address": "0x8398d48b07ce56b3451aba51a7c63b7088406414",
        "chainId": "1"
      }
    ]
  },
  {
    "userId": "630744",
    "userAddress": "0x225869ad63e26e87f9fe7993016ed3bdad4bb8eb",
    "profileDisplayName": "Christina",
    "profileHandle": "1984sparkskristo",
    "connectedAddresses": [
      {
        "address": "0xe72b3fd35d0afb32463c1f6fde02301bc6a85d97",
        "chainId": "1"
      },
      {
        "address": "77MAGD1CHk4UBJmAEYsdneuysKnjABEGgWfZ9yG6ySgz",
        "chainId": "900"
      }
    ]
  },
  {
    "userId": "630745",
    "userAddress": "0xbb393c86fdbd82764429a67d90fd583dccaffbee",
    "profileDisplayName": "1dzz",
    "profileHandle": "1dzz",
    "connectedAddresses": [
      {
        "address": "0x5fc042c9e243e1fa13743b6cae42829b74ef6f63",
        "chainId": "1"
      }
    ]
  },
  {
    "userId": "630746",
    "userAddress": "0xf7da0cdfe78e11a852b8e1f5efa6470d68d186b9",
    "profileDisplayName": "Jarvis",
    "profileHandle": "jarvisminnich",
    "connectedAddresses": [
      {
        "address": "0xa1c17778e056493fa7a24537caac68f08a113b2f",
        "chainId": "1"
      }
    ]
  },
  {
    "userId": "630747",
    "userAddress": "0xcd25b78a604ec776346f82347f0ce6587300ad97",
    "profileDisplayName": "Parker",
    "profileHandle": "numun",
    "connectedAddresses": [
      {
        "address": "0x024f44b6adcb5d7e8b9d795781627bf32ffa42d8",
        "chainId": "1"
      }
    ]
  },
  {
    "userId": "630748",
    "userAddress": "0xe7c8b4ba0f3ff79bc6c73902464d26a9901094cf",
    "profileDisplayName": "Evan",
    "profileHandle": "zorin",
    "connectedAddresses": [
      {
        "address": "0x879040c2e97c266f8f2f62e986ede42b0a1d21a6",
        "chainId": "1"
      }
    ]
  },
  {
    "userId": "630749",
    "userAddress": "0xa2f2bc94b5e4a936f1dfa693618d67f2c2f20e3b",
    "profileDisplayName": "Jason",
    "profileHandle": "paxes",
    "connectedAddresses": [
      {
        "address": "0x56bb965ec4062118a4900f1be61e988a31c95c72",
        "chainId": "1"
      }
    ]
  },
  {
    "userId": "630750",
    "userAddress": "0xf2880d805593509bb17a8aea29855ffd135ca062",
    "profileDisplayName": "Jace",
    "profileHandle": "fugle",
    "connectedAddresses": [
      {
        "address": "0xf6b11770cf58bd76587de38df96013cb5ccf1bb2",
        "chainId": "1"
      }
    ]
  },
  {
    "userId": "630751",
    "userAddress": "0xad593ad3ff33a2e1858ba5901db2dfde1c53fcce",
    "profileDisplayName": "Abaya",
    "profileHandle": "abaya",
    "connectedAddresses": []
  },
  {
    "userId": "630752",
    "userAddress": "0x295d9951e056effd6de996cdaef7eafc67a492f8",
    "profileDisplayName": "Evgenii",
    "profileHandle": "dantonov4",
    "connectedAddresses": []
  },
  {
    "userId": "630753",
    "userAddress": "0x87af95e7e5f7e9207cf9bae5d48decc9351c668f",
    "profileDisplayName": "Sirmeekay",
    "profileHandle": "sirmeekay",
    "connectedAddresses": [
      {
        "address": "0x523f655dc663161349e7a8a85bb085449ff15008",
        "chainId": "1"
      }
    ]
  },
  {
    "userId": "630754",
    "userAddress": "0x8e5f2e54419f77bb849d19b8a6615e45689d7070",
    "profileDisplayName": "",
    "profileHandle": "skreza",
    "connectedAddresses": []
  },
  {
    "userId": "630755",
    "userAddress": "0xf58b63ba590c714306c285af061a9ee97ba85ee3",
    "profileDisplayName": "Indigo Rain",
    "profileHandle": "indiga",
    "connectedAddresses": [
      {
        "address": "0xc97bdf7101e0acd49926a6ed2fd23d0b3a895049",
        "chainId": "1"
      },
      {
        "address": "6ewUknpT3FLUtPiCSBEj5ZUqB5Sfa6PXuQghrvXW56jR",
        "chainId": "900"
      }
    ]
  },
  {
    "userId": "630756",
    "userAddress": "0x4fefba1a700d76a2334f968ab11e9de3f218906b",
    "profileDisplayName": "limasufiya19",
    "profileHandle": "limasufiya19",
    "connectedAddresses": [
      {
        "address": "0xc32704c2a852e793446c6f802ce177344280a4dc",
        "chainId": "1"
      },
      {
        "address": "2pdbeqgUiJYYEMdqqkhkPmQMsFt7rQgU5V4WytN5WeXy",
        "chainId": "900"
      }
    ]
  },
  {
    "userId": "630757",
    "userAddress": "0x6ebd7daa1fd69562dbac850eca6e61358eccbf52",
    "profileDisplayName": "Miller213",
    "profileHandle": "miller213",
    "connectedAddresses": [
      {
        "address": "0x566649fb0c084e774a5e66f973ff6dffba31db48",
        "chainId": "1"
      }
    ]
  },
  {
    "userId": "630758",
    "userAddress": "0x8733c441ac0130300e567ad12a9217d14959c6e8",
    "profileDisplayName": "clairreeeee",
    "profileHandle": "claireeeee",
    "connectedAddresses": []
  },
  {
    "userId": "630759",
    "userAddress": "0xc702c23deed8880546bddabe107de05686952911",
    "profileDisplayName": "Jones108",
    "profileHandle": "jones108",
    "connectedAddresses": [
      {
        "address": "0xa870565a804e1eb97e0c4c12c85dc5c072420ce4",
        "chainId": "1"
      }
    ]
  },
  {
    "userId": "630760",
    "userAddress": "0x630906c599cc6df04f10350deb10be69a207940a",
    "profileDisplayName": "BlissfulSoul",
    "profileHandle": "fjsjcjc",
    "connectedAddresses": [
      {
        "address": "0x551b2da2a81974f27586ab70ee260ad93d7a7721",
        "chainId": "1"
      }
    ]
  },
  {
    "userId": "630762",
    "userAddress": "0x23a4e7595372e535f761be98c7ba1deb87f01330",
    "profileDisplayName": "Samrat Swargam",
    "profileHandle": "samrat",
    "connectedAddresses": []
  },
  {
    "userId": "630763",
    "userAddress": "0xdf075eff1dda612b1bdf55abb1f49f539b4c195e",
    "profileDisplayName": "Kyle",
    "profileHandle": "jaidyn1984murill",
    "connectedAddresses": [
      {
        "address": "0xd6c0c5d2902ab80fbfecd3ea29f661509a0b35f5",
        "chainId": "1"
      },
      {
        "address": "H3uGVKzjYZiXw4H9DDkL5Z8kQUktskS6u1ZMsLB82jKC",
        "chainId": "900"
      }
    ]
  },
  {
    "userId": "630764",
    "userAddress": "0x1329e4c59e4b3e8c17fd06fc52c1b603ccf8814d",
    "profileDisplayName": "Crypto Boss",
    "profileHandle": "goykhman",
    "connectedAddresses": [
      {
        "address": "0x9d3551a171b11239de2ff34aecfcd93890aa1ed1",
        "chainId": "1"
      }
    ]
  },
  {
    "userId": "630765",
    "userAddress": "0xabd6e6fc2b53fc1a116a33a39c0bf3c79ffe73ea",
    "profileDisplayName": "kk78",
    "profileHandle": "kk78",
    "connectedAddresses": [
      {
        "address": "0xde405aae2d13e211f212537f8db4bdd73832d8c4",
        "chainId": "1"
      }
    ]
  },
  {
    "userId": "630767",
    "userAddress": "0x436c7177424c0061bc6e0a440d61ae149f526f60",
    "profileDisplayName": "yianramendoza",
    "profileHandle": "yianramendoza",
    "connectedAddresses": []
  },
  {
    "userId": "630768",
    "userAddress": "0xc8b3b2a2a2a19b63368a424cbc794022d6d8f7a0",
    "profileDisplayName": "sarmasahi90",
    "profileHandle": "sarmasahi90",
    "connectedAddresses": [
      {
        "address": "0x8e7d6f5f76189115ad286e35936a6e59832d073b",
        "chainId": "1"
      },
      {
        "address": "3Y5wJCmVNaeyuEnH2xxk9Uxs7fo1jS9ifYHZfiYGs78p",
        "chainId": "900"
      }
    ]
  },
  {
    "userId": "630769",
    "userAddress": "0x663eb44292c780a8e7410aff5f4dbc7116dbf380",
    "profileDisplayName": "Mykola",
    "profileHandle": "inf1nity3",
    "connectedAddresses": []
  },
  {
    "userId": "630770",
    "userAddress": "0xe6941b422825a2f252c3a58cc4e9b5129efb91ec",
    "profileDisplayName": "German",
    "profileHandle": "gaman",
    "connectedAddresses": [
      {
        "address": "0x0c16ee0c352947948d69e4b4ad5fc89a6ae0db5f",
        "chainId": "1"
      }
    ]
  },
  {
    "userId": "630771",
    "userAddress": "0xcb738c6c84efd947f2ed53b25f536059b99d3e63",
    "profileDisplayName": "Slither🎭",
    "profileHandle": "slither",
    "connectedAddresses": [
      {
        "address": "0x4d51c2e16004911fe9bd048dfe9989d72a6d1fb9",
        "chainId": "1"
      },
      {
        "address": "2hyzk7nbQ7dVLMXUzG7Hg9YktULEpjDk3q4jVEzSzHaw",
        "chainId": "900"
      }
    ]
  },
  {
    "userId": "630772",
    "userAddress": "0xd614d97373c9c04400bee0dbaf056c8ce0e7229d",
    "profileDisplayName": "宋柘",
    "profileHandle": "scortesia",
    "connectedAddresses": []
  },
  {
    "userId": "630773",
    "userAddress": "0xbd5f6ce4c72e69bca2000c10d360b02cefdcd58c",
    "profileDisplayName": "Garcia51",
    "profileHandle": "garcia51",
    "connectedAddresses": [
      {
        "address": "0xd63ad6fb6c44bd2347395ec882778e1f69b7fe95",
        "chainId": "1"
      }
    ]
  },
  {
    "userId": "630774",
    "userAddress": "0x5608cbfab2174cd2cbf5e947f4bc268f5d4aeea3",
    "profileDisplayName": "Abigail",
    "profileHandle": "kaseyortega1981",
    "connectedAddresses": [
      {
        "address": "0xde5baca1b167af92580ad679ec84436d542e94ea",
        "chainId": "1"
      },
      {
        "address": "9Unj4XFELS9qAiPyhesoxABFgLm5KAmkMMk49NSj1TgZ",
        "chainId": "900"
      }
    ]
  },
  {
    "userId": "630775",
    "userAddress": "0xfd9f6179d9e1047908d293f2fd21502c631e123a",
    "profileDisplayName": "PaulaMinerva\n",
    "profileHandle": "paulaminerva",
    "connectedAddresses": [
      {
        "address": "0xe3bae7d4c49bf51ae2bdde3373082183a544c035",
        "chainId": "1"
      }
    ]
  },
  {
    "userId": "630776",
    "userAddress": "0x0227fdfd97fa0def372b6fb1f865353ccdd7d30b",
    "profileDisplayName": "Davis9",
    "profileHandle": "davis9",
    "connectedAddresses": [
      {
        "address": "0xc09b318df8cbdb70f0af3c7750093dc23b56f88d",
        "chainId": "1"
      }
    ]
  },
  {
    "userId": "630777",
    "userAddress": "0x87e81952175215cc83564b571f27a0d3f2712759",
    "profileDisplayName": "Jamesrgd",
    "profileHandle": "jamesrgd",
    "connectedAddresses": [
      {
        "address": "0x25980ab1556ebc43a7fbc1374717cf8b8980e7aa",
        "chainId": "1"
      }
    ]
  },
  {
    "userId": "630778",
    "userAddress": "0x61fe66afbf5d32cbdfeb107a2ef5ee2174080c0c",
    "profileDisplayName": "Ruslan Bezsmertnyi",
    "profileHandle": "lp1927",
    "connectedAddresses": [
      {
        "address": "0xa4b437b4a5bbfdf3ac433bc554db5f57e02d01d7",
        "chainId": "1"
      },
      {
        "address": "GVPbX7E3ku8vfW9aoWeypYft995yepGsPQ1oWZnNv3f3",
        "chainId": "900"
      }
    ]
  },
  {
    "userId": "630779",
    "userAddress": "0xd5ffe81e501e410d8b5f89d6ef1d9c1e7cbe9c2a",
    "profileDisplayName": "ninamalory",
    "profileHandle": "ninamalory",
    "connectedAddresses": [
      {
        "address": "0xf5aa0a2d59841657e496fc10a7ce59b99e47cd64",
        "chainId": "1"
      }
    ]
  },
  {
    "userId": "630780",
    "userAddress": "0x897ece336795c64d1839ed3f12398c697e024355",
    "profileDisplayName": "EvelynHoly\n",
    "profileHandle": "evelynholy",
    "connectedAddresses": [
      {
        "address": "0xdd295577046c7328b76d080adc8840c8b7ce4398",
        "chainId": "1"
      }
    ]
  },
  {
    "userId": "630781",
    "userAddress": "0x96f48578a4590c171959fa6d8ba471fd9eca7ea7",
    "profileDisplayName": "FernSoldier\n",
    "profileHandle": "fernsoldier",
    "connectedAddresses": [
      {
        "address": "0x87481ed88051078033c2fedaf42f0774a3778d04",
        "chainId": "1"
      }
    ]
  },
  {
    "userId": "630782",
    "userAddress": "0x7980b0fb6bb27fa763f2cdf46bd545566bb930e0",
    "profileDisplayName": "alaca",
    "profileHandle": "alaca",
    "connectedAddresses": []
  },
  {
    "userId": "630783",
    "userAddress": "0xf4d37ff27af16a074dc9f9dfd668cfed468faaf3",
    "profileDisplayName": "ffff4",
    "profileHandle": "xfxwthf197",
    "connectedAddresses": [
      {
        "address": "0x82ec1842d73d0f564a8fba448d9b849c8924ed40",
        "chainId": "1"
      }
    ]
  },
  {
    "userId": "630784",
    "userAddress": "0x7b98c6dd523d451aabec863441c3df1ca746ee64",
    "profileDisplayName": "Rebecca",
    "profileHandle": "1991anayacumming",
    "connectedAddresses": [
      {
        "address": "0xa99b07127aaa2c0868f1f8fcfed515c5a0a2dfdf",
        "chainId": "1"
      },
      {
        "address": "Gtg5dxq57WpPc832jvufnDSedtrS2VG8D4PyZNUJzDbh",
        "chainId": "900"
      }
    ]
  },
  {
    "userId": "630785",
    "userAddress": "0x846959be6dd170320d077f8b7cba0a45ad133fcc",
    "profileDisplayName": "MartaFair-Haired\n",
    "profileHandle": "martafair-haired",
    "connectedAddresses": [
      {
        "address": "0xfaaba941348dd50298f0557258049674d57a99be",
        "chainId": "1"
      }
    ]
  },
  {
    "userId": "630786",
    "userAddress": "0xec8aab394769e844634fa2fc1a67a89175d2c4d4",
    "profileDisplayName": "Terry Howard",
    "profileHandle": "techier",
    "connectedAddresses": [
      {
        "address": "0x8ea4351bdd70cd165017016736e2ccaaeeffe5c1",
        "chainId": "1"
      }
    ]
  },
  {
    "userId": "630787",
    "userAddress": "0x2369c761e748c9402e5c979628775249e46c266d",
    "profileDisplayName": "MysticJourney",
    "profileHandle": "fjsidbfdh",
    "connectedAddresses": [
      {
        "address": "0x9eb1b99afab4367935a183b01f7149ca5f014a32",
        "chainId": "1"
      }
    ]
  },
  {
    "userId": "630788",
    "userAddress": "0xf7cb6e51770fd10b2b48a98bfdba428299fb93cf",
    "profileDisplayName": "TowerVictor\n",
    "profileHandle": "towervictor",
    "connectedAddresses": [
      {
        "address": "0xaba6d841b345135f4a48a6691e891988e8914e32",
        "chainId": "1"
      }
    ]
  },
  {
    "userId": "630789",
    "userAddress": "0x4a2f07fed24ef2e300c5ce15c4ce48a192c2a317",
    "profileDisplayName": "IdaOpal\n",
    "profileHandle": "idaopal",
    "connectedAddresses": [
      {
        "address": "0x2d249961175d4c201de6c60ee50d59f8ad2a1f36",
        "chainId": "1"
      }
    ]
  },
  {
    "userId": "630790",
    "userAddress": "0xddd1b5578a179681a34ed50989f5134ffa5f23a9",
    "profileDisplayName": "Richfront",
    "profileHandle": "padurich",
    "connectedAddresses": [
      {
        "address": "0xdb73539a04f98e439537a58fb37c144aedd79703",
        "chainId": "1"
      }
    ]
  },
  {
    "userId": "630791",
    "userAddress": "0xb0bd198a93dd77db485028afb4693ded2be1d0fb",
    "profileDisplayName": "",
    "profileHandle": "eltonmieltonmits",
    "connectedAddresses": []
  },
  {
    "userId": "630792",
    "userAddress": "0xc48943138e13fcbad068dd2124c257539f5f82c1",
    "profileDisplayName": "ebadnerb",
    "profileHandle": "evadnerb",
    "connectedAddresses": [
      {
        "address": "0x95002a360401721e1df07751151121ca54a2082e",
        "chainId": "1"
      },
      {
        "address": "HMGN1bbrt7CUSY4K1zLK43a8QzTJviw9hbxB4nNKkWyE",
        "chainId": "900"
      }
    ]
  },
  {
    "userId": "630793",
    "userAddress": "0x62cc22bd6795658290e8450181495bcfb43e5cc8",
    "profileDisplayName": "",
    "profileHandle": "pritha88",
    "connectedAddresses": []
  },
  {
    "userId": "630794",
    "userAddress": "0x1888bec3492a2475a24762c5f4c29af5d571bc15",
    "profileDisplayName": "schnellemar1977",
    "profileHandle": "schnellemar1977",
    "connectedAddresses": []
  },
  {
    "userId": "630795",
    "userAddress": "0xcd8149d7df36a2c8f5f38b7977053074ee45322f",
    "profileDisplayName": "21dm",
    "profileHandle": "21dm",
    "connectedAddresses": [
      {
        "address": "0x3dc67e1edb3d97c664d18876182360d0dd6e2964",
        "chainId": "1"
      }
    ]
  },
  {
    "userId": "630796",
    "userAddress": "0xc91bf389e65972eadf953dcaf141269e4ad3f335",
    "profileDisplayName": "Yana",
    "profileHandle": "yaniti",
    "connectedAddresses": [
      {
        "address": "0xb3297a80bc1033c6f7b3474a59121b520eecaff4",
        "chainId": "1"
      }
    ]
  },
  {
    "userId": "630797",
    "userAddress": "0xe5fff5c7f401fa15632a77d2a17c17e61d336240",
    "profileDisplayName": "",
    "profileHandle": "xenavine8030",
    "connectedAddresses": []
  },
  {
    "userId": "630798",
    "userAddress": "0x6e03021fca7fbddab29e90bc4dcf81f547935382",
    "profileDisplayName": "Srinath",
    "profileHandle": "srinathreddy",
    "connectedAddresses": []
  }
]
